<SYSTEM>
    <DEVICE>
        <name>58852</name>
        <emission>8</emission>
        <speed>40</speed>
    </DEVICE>
    <JOB>
        <jobNumber>56622</jobNumber>
        <pageCount>10</pageCount>
        <userName>NoahMasudi</userName>
    </JOB>
    <JOB>
        <jobNumber>12354</jobNumber>
        <pageCount>2</pageCount>
        <userName>AdamBoustta</userName>
    </JOB>
    <JOB>
        <jobNumber>23424</jobNumber>
        <pageCount>9</pageCount>
        <userName>Khabib</userName>
    </JOB>
</SYSTEM>